Metadata-Version: 2.1
Name: juan_stats
Version: 1.3
Summary: Probability Density Function  calculator for Binmonial and Gaussian distributions
Author: Juan P
